exca/__init__.py
exca/base.py
exca/cachedict.py
exca/confdict.py
exca/dumperloader.py
exca/helpers.py
exca/logconf.py
exca/map.py
exca/py.typed
exca/slurm.py
exca/task.py
exca/test_base.py
exca/test_cachedict.py
exca/test_compat.py
exca/test_confdict.py
exca/test_dumperloader.py
exca/test_helpers.py
exca/test_localmap.py
exca/test_map.py
exca/test_safeguard.py
exca/test_submit.py
exca/test_task.py
exca/test_utils.py
exca/test_workdir.py
exca/utils.py
exca/workdir.py
exca/chain/__init__.py
exca/chain/backends.py
exca/chain/steps.py
exca/chain/test_backends.py
exca/chain/test_steps.py
exca-0.5.9.dist-info/licenses/LICENSE
exca-0.5.9.dist-info/METADATA
exca-0.5.9.dist-info/WHEEL
exca-0.5.9.dist-info/top_level.txt
exca-0.5.9.dist-info/RECORD
