Metadata-Version: 2.4
Name: exca
Version: 0.5.9
Summary: Execution and caching tool for python
Author: Meta FAIR
Project-URL: Source, https://github.com/facebookresearch/exca
Project-URL: Tracker, https://github.com/facebookresearch/exca/issues
Requires-Python: >=3.10
License-File: LICENSE
Requires-Dist: numpy>=1.19
Requires-Dist: pyyaml>=6.0
Requires-Dist: pydantic>=2.5.0
Requires-Dist: submitit>=1.5.1
Requires-Dist: orjson
Provides-Extra: dev
Requires-Dist: pandas>=2.2.2; extra == "dev"
Requires-Dist: torch>=2.0.1; extra == "dev"
Requires-Dist: mne>=1.4.0; extra == "dev"
Requires-Dist: pybv>=0.7.6; extra == "dev"
Requires-Dist: nibabel>=5.1.0; extra == "dev"
Requires-Dist: pyarrow>=17.0.0; extra == "dev"
Requires-Dist: pytest>=7.4.0; extra == "dev"
Requires-Dist: pytest-markdown-docs>=0.5.0; extra == "dev"
Requires-Dist: psutil>=6.1.1; extra == "dev"
Requires-Dist: pip; extra == "dev"
Requires-Dist: tqdm>=4.65.0; extra == "dev"
Requires-Dist: black==24.3.0; extra == "dev"
Requires-Dist: isort==5.12.0; extra == "dev"
Requires-Dist: pre-commit>=3.0.0; extra == "dev"
Requires-Dist: mypy>=1.11.0; extra == "dev"
Requires-Dist: pylint>=2.13.9; extra == "dev"
Requires-Dist: flake8; extra == "dev"
Requires-Dist: pandas-stubs; extra == "dev"
Requires-Dist: types-PyYAML; extra == "dev"
Requires-Dist: types-setuptools; extra == "dev"
Requires-Dist: types-tqdm; extra == "dev"
Requires-Dist: types-psutil; extra == "dev"
Requires-Dist: sphinx>=7.4.7; extra == "dev"
Requires-Dist: myst-parser>=3.0.1; extra == "dev"
Dynamic: license-file
